spectacles/__init__.py
spectacles/cli.py
spectacles/client.py
spectacles/exceptions.py
spectacles/logger.py
spectacles/lookml.py
spectacles/models.py
spectacles/printer.py
spectacles/project_select.py
spectacles/py.typed
spectacles/runner.py
spectacles/utils.py
spectacles/validators/__init__.py
spectacles/validators/content.py
spectacles/validators/data_test.py
spectacles/validators/lookml.py
spectacles/validators/sql.py
spectacles-2.4.16.dist-info/LICENSE
spectacles-2.4.16.dist-info/METADATA
spectacles-2.4.16.dist-info/WHEEL
spectacles-2.4.16.dist-info/entry_points.txt
spectacles-2.4.16.dist-info/RECORD
