Metadata-Version: 2.3
Name: spectacles
Version: 2.4.16
Summary: A command-line, continuous integration tool for Looker and LookML.
License: MIT
Keywords: Looker,LookML,CI,continuous integration,testing,validation
Author: Spectacles
Author-email: hello@spectacles.dev
Requires-Python: >=3.9,<4.0
Classifier: Development Status :: 5 - Production/Stable
Classifier: Environment :: Console
Classifier: Intended Audience :: Developers
Classifier: Intended Audience :: Information Technology
Classifier: License :: OSI Approved :: MIT License
Classifier: Operating System :: OS Independent
Classifier: Programming Language :: Python :: 3
Classifier: Programming Language :: Python :: 3.9
Classifier: Programming Language :: Python :: 3.10
Classifier: Programming Language :: Python :: 3.11
Classifier: Programming Language :: Python :: 3.12
Classifier: Programming Language :: Python :: 3.13
Classifier: Topic :: Software Development :: Quality Assurance
Classifier: Topic :: Software Development :: Testing
Classifier: Topic :: Utilities
Requires-Dist: PyYAML (>=6.0.1,<7.0.0)
Requires-Dist: aiocache (>=0.12.2,<0.13.0)
Requires-Dist: backoff (>=2.1,<3.0)
Requires-Dist: colorama (>=0.4.6,<0.5.0)
Requires-Dist: httpcore (>=1.0.3)
Requires-Dist: httpx (>=0.26.0,<0.27.0)
Requires-Dist: pydantic (>=2.5.3,<3.0.0)
Requires-Dist: segment-analytics-python (==2.2.3)
Requires-Dist: tabulate (>=0.9.0,<0.10.0)
Requires-Dist: typing-extensions (>=4.9.0,<5.0.0)
Project-URL: Documentation, https://docs.spectacles.dev/cli/tutorials/getting-started
Project-URL: Homepage, https://spectacles.dev
Project-URL: Repository, https://github.com/spectacles-ci/spectacles
